<annotation>
	<folder></folder>
	<filename>frame--335-_jpg.rf.77861fd7c1364c67544692bd7706dade.jpg</filename>
	<path>frame--335-_jpg.rf.77861fd7c1364c67544692bd7706dade.jpg</path>
	<source>
		<database>roboflow.ai</database>
	</source>
	<size>
		<width>416</width>
		<height>416</height>
		<depth>3</depth>
	</size>
	<segmented>0</segmented>
	<object>
		<name>LicensePlate</name>
		<pose>Unspecified</pose>
		<truncated>0</truncated>
		<difficult>0</difficult>
		<occluded>0</occluded>
		<bndbox>
			<xmin>129</xmin>
			<xmax>182</xmax>
			<ymin>233</ymin>
			<ymax>266</ymax>
		</bndbox>
	</object>
	<object>
		<name>LeadTruck</name>
		<pose>Unspecified</pose>
		<truncated>0</truncated>
		<difficult>0</difficult>
		<occluded>0</occluded>
		<bndbox>
			<xmin>92</xmin>
			<xmax>210</xmax>
			<ymin>128</ymin>
			<ymax>291</ymax>
		</bndbox>
	</object>
</annotation>
